vitexpy.py
vitexpy-1.0.4.dist-info/LICENSE
vitexpy-1.0.4.dist-info/WHEEL
vitexpy-1.0.4.dist-info/METADATA
vitexpy-1.0.4.dist-info/RECORD
