Metadata-Version: 2.1
Name: vitexpy
Version: 1.0.4
Summary: PYTHON WRAPPER FOR VITEX.NET API v2
Author-email: ` blacktyger <blacktyg3r@gmail.com>
Classifier: License :: OSI Approved :: MIT License
Project-URL: Home, https://github.com/blacktyg3r
